[{"date": "2018-01-07 00:00:00", "centroid_lon": -80.10269179688177, "centroid_lat": 34.97381293623332, "state": "37_North Carolina", "county": "007_Anson", "type": "TCI", "mean": -1.0}, {"date": "2018-01-07 00:00:00", "centroid_lon": -81.54640572406205, "centroid_lat": 35.95302854449218, "state": "37_North Carolina", "county": "027_Caldwell", "type": "TCI", "mean": -1.0}, {"date": "2018-01-07 00:00:00", "centroid_lon": -84.06347829162283, "centroid_lat": 35.13387299872851, "state": "37_North Carolina", "county": "039_Cherokee", "type": "TCI", "mean": -1.0}, {"date": "2018-01-07 00:00:00", "centroid_lon": -77.09389404831583, "centroid_lat": 35.12485682346288, "state": "37_North Carolina", "county": "049_Craven", "type": "TCI", "mean": -1.0}, {"date": "2018-01-07 00:00:00", "centroid_lon": -75.79799395035838, "centroid_lat": 35.779537285786496, "state": "37_North Carolina", "county": "055_Dare", "type": "TCI", "mean": -1.0}, {"date": "2018-01-07 00:00:00", "centroid_lon": -80.54447339564811, "centroid_lat": 35.9291113343129, "state": "37_North Carolina", "county": "059_Davie", "type": "TCI", "mean": -1.0}, {"date": "2018-01-07 00:00:00", "centroid_lon": -78.28570287592468, "centroid_lat": 36.08275501760047, "state": "37_North Carolina", "county": "069_Franklin", "type": "TCI", "mean": -1.0}, {"date": "2018-01-07 00:00:00", "centroid_lon": -77.65173465817095, "centroid_lat": 36.257446623910205, "state": "37_North Carolina", "county": "083_Halifax", "type": "TCI", "mean": -1.0}, {"date": "2018-01-07 00:00:00", "centroid_lon": -76.98200271120336, "centroid_lat": 36.35906558693843, "state": "37_North Carolina", "county": "091_Hertford", "type": "TCI", "mean": -1.0}, {"date": "2018-01-07 00:00:00", "centroid_lon": -79.2372635327355, "centroid_lat": 35.01754332093964, "state": "37_North Carolina", "county": "093_Hoke", "type": "TCI", "mean": -1.0}, {"date": "2018-01-07 00:00:00", "centroid_lon": -83.14082687764743, "centroid_lat": 35.28753604670398, "state": "37_North Carolina", "county": "099_Jackson", "type": "TCI", "mean": -1.0}, {"date": "2018-01-07 00:00:00", "centroid_lon": -82.04932312749307, "centroid_lat": 35.6816998119451, "state": "37_North Carolina", "county": "111_McDowell", "type": "TCI", "mean": -1.0}, {"date": "2018-01-07 00:00:00", "centroid_lon": -77.1092476903645, "centroid_lat": 35.843212718512845, "state": "37_North Carolina", "county": "117_Martin", "type": "TCI", "mean": -1.0}, {"date": "2018-01-07 00:00:00", "centroid_lon": -77.98643325785983, "centroid_lat": 35.96725094984758, "state": "37_North Carolina", "county": "127_Nash", "type": "TCI", "mean": -1.0}, {"date": "2018-01-07 00:00:00", "centroid_lon": -79.48037763934069, "centroid_lat": 34.84089928864632, "state": "37_North Carolina", "county": "165_Scotland", "type": "TCI", "mean": -1.0}, {"date": "2018-01-07 00:00:00", "centroid_lon": -82.79820829544566, "centroid_lat": 35.202140881540004, "state": "37_North Carolina", "county": "175_Transylvania", "type": "TCI", "mean": -1.0}, {"date": "2018-01-07 00:00:00", "centroid_lon": -82.3076248573456, "centroid_lat": 35.89894457055489, "state": "37_North Carolina", "county": "199_Yancey", "type": "TCI", "mean": -1.0}, {"date": "2018-01-07 00:00:00", "centroid_lon": -81.50050206898705, "centroid_lat": 36.43447673458056, "state": "37_North Carolina", "county": "009_Ashe", "type": "TCI", "mean": -1.0}, {"date": "2018-01-07 00:00:00", "centroid_lon": -76.85978138890117, "centroid_lat": 35.494001822040815, "state": "37_North Carolina", "county": "013_Beaufort", "type": "TCI", "mean": -1.0}, {"date": "2018-01-07 00:00:00", "centroid_lon": -78.56363614838952, "centroid_lat": 34.6145869416746, "state": "37_North Carolina", "county": "017_Bladen", "type": "TCI", "mean": -1.0}, {"date": "2018-01-07 00:00:00", "centroid_lon": -81.70477517320451, "centroid_lat": 35.74961161692438, "state": "37_North Carolina", "county": "023_Burke", "type": "TCI", "mean": -1.0}, {"date": "2018-01-07 00:00:00", "centroid_lon": -79.25528760750444, "centroid_lat": 35.7025737922762, "state": "37_North Carolina", "county": "037_Chatham", "type": "TCI", "mean": -1.0}, {"date": "2018-01-07 00:00:00", "centroid_lon": -83.75017335105478, "centroid_lat": 35.057217686430604, "state": "37_North Carolina", "county": "043_Clay", "type": "TCI", "mean": -1.0}, {"date": "2018-01-07 00:00:00", "centroid_lon": -76.00594023553712, "centroid_lat": 36.40307992357336, "state": "37_North Carolina", "county": "053_Currituck", "type": "TCI", "mean": -1.0}, {"date": "2018-01-07 00:00:00", "centroid_lon": -80.21274505395438, "centroid_lat": 35.79335503643409, "state": "37_North Carolina", "county": "057_Davidson", "type": "TCI", "mean": -1.0}, {"date": "2018-01-07 00:00:00", "centroid_lon": -77.59706062049973, "centroid_lat": 35.912881152513066, "state": "37_North Carolina", "county": "065_Edgecombe", "type": "TCI", "mean": -1.0}, {"date": "2018-01-07 00:00:00", "centroid_lon": -83.83348116242213, "centroid_lat": 35.350167472177745, "state": "37_North Carolina", "county": "075_Graham", "type": "TCI", "mean": -1.0}, {"date": "2018-01-07 00:00:00", "centroid_lon": -78.86941473556807, "centroid_lat": 35.36863299235536, "state": "37_North Carolina", "county": "085_Harnett", "type": "TCI", "mean": -1.0}, {"date": "2018-01-07 00:00:00", "centroid_lon": -82.479969639877, "centroid_lat": 35.33631095035395, "state": "37_North Carolina", "county": "089_Henderson", "type": "TCI", "mean": -1.0}, {"date": "2018-01-07 00:00:00", "centroid_lon": -76.25080937261622, "centroid_lat": 35.53048716223177, "state": "37_North Carolina", "county": "095_Hyde", "type": "TCI", "mean": -1.0}, {"date": "2018-01-07 00:00:00", "centroid_lon": -77.35518726325826, "centroid_lat": 35.02172492774331, "state": "37_North Carolina", "county": "103_Jones", "type": "TCI", "mean": -1.0}, {"date": "2018-01-07 00:00:00", "centroid_lon": -82.70576464432698, "centroid_lat": 35.85801433155336, "state": "37_North Carolina", "county": "115_Madison", "type": "TCI", "mean": -1.0}, {"date": "2018-01-07 00:00:00", "centroid_lon": -79.90548646611734, "centroid_lat": 35.332465125105216, "state": "37_North Carolina", "county": "123_Montgomery", "type": "TCI", "mean": -1.0}, {"date": "2018-01-07 00:00:00", "centroid_lon": -77.43208152303728, "centroid_lat": 34.73212750139306, "state": "37_North Carolina", "county": "133_Onslow", "type": "TCI", "mean": -1.0}, {"date": "2018-01-07 00:00:00", "centroid_lon": -76.74069804344519, "centroid_lat": 35.14345018969962, "state": "37_North Carolina", "county": "137_Pamlico", "type": "TCI", "mean": -1.0}, {"date": "2018-01-07 00:00:00", "centroid_lon": -82.16966168177338, "centroid_lat": 35.279274683301765, "state": "37_North Carolina", "county": "149_Polk", "type": "TCI", "mean": -1.0}, {"date": "2018-01-07 00:00:00", "centroid_lon": -79.74784832339414, "centroid_lat": 35.0059392182002, "state": "37_North Carolina", "county": "153_Richmond", "type": "TCI", "mean": -1.0}, {"date": "2018-01-07 00:00:00", "centroid_lon": -81.91984346745981, "centroid_lat": 35.402565091023604, "state": "37_North Carolina", "county": "161_Rutherford", "type": "TCI", "mean": -1.0}, {"date": "2018-01-07 00:00:00", "centroid_lon": -78.37138578943149, "centroid_lat": 34.99154033661567, "state": "37_North Carolina", "county": "163_Sampson", "type": "TCI", "mean": -1.0}, {"date": "2018-01-07 00:00:00", "centroid_lon": -76.20895098388708, "centroid_lat": 35.81720597863048, "state": "37_North Carolina", "county": "177_Tyrrell", "type": "TCI", "mean": -1.0}, {"date": "2018-01-07 00:00:00", "centroid_lon": -76.20636217072874, "centroid_lat": 36.387704168595775, "state": "37_North Carolina", "county": "029_Camden", "type": "TCI", "mean": -1.0}, {"date": "2018-01-07 00:00:00", "centroid_lon": -79.17147916668007, "centroid_lat": 35.475189724170555, "state": "37_North Carolina", "county": "105_Lee", "type": "TCI", "mean": -1.0}, {"date": "2018-01-07 00:00:00", "centroid_lon": -79.48138043988601, "centroid_lat": 35.31064402510283, "state": "37_North Carolina", "county": "125_Moore", "type": "TCI", "mean": -1.0}, {"date": "2018-01-07 00:00:00", "centroid_lon": -82.53011352598989, "centroid_lat": 35.61118328541394, "state": "37_North Carolina", "county": "021_Buncombe", "type": "TCI", "mean": -1.0}, {"date": "2018-01-07 00:00:00", "centroid_lon": -77.64124599796058, "centroid_lat": 35.238773407964715, "state": "37_North Carolina", "county": "107_Lenoir", "type": "TCI", "mean": -1.0}, {"date": "2018-01-07 00:00:00", "centroid_lon": -78.97178238908526, "centroid_lat": 36.39000490625264, "state": "37_North Carolina", "county": "145_Person", "type": "TCI", "mean": -1.0}, {"date": "2018-01-07 00:00:00", "centroid_lon": -81.16339435837136, "centroid_lat": 36.20627886131307, "state": "37_North Carolina", "county": "193_Wilkes", "type": "TCI", "mean": -1.0}, {"date": "2018-01-07 00:00:00", "centroid_lon": -76.97866800591429, "centroid_lat": 36.06616726904903, "state": "37_North Carolina", "county": "015_Bertie", "type": "TCI", "mean": -1.0}, {"date": "2018-01-07 00:00:00", "centroid_lon": -78.36571445577421, "centroid_lat": 35.51781456622617, "state": "37_North Carolina", "county": "101_Johnston", "type": "TCI", "mean": -1.0}, {"date": "2018-01-07 00:00:00", "centroid_lon": -77.39685937097359, "centroid_lat": 36.41776207122251, "state": "37_North Carolina", "county": "131_Northampton", "type": "TCI", "mean": -1.0}, {"date": "2018-01-07 00:00:00", "centroid_lon": -80.52478950429492, "centroid_lat": 35.63947931146283, "state": "37_North Carolina", "county": "159_Rowan", "type": "TCI", "mean": -1.0}, {"date": "2018-01-07 00:00:00", "centroid_lon": -78.6503109077999, "centroid_lat": 35.790256884742355, "state": "37_North Carolina", "county": "183_Wake", "type": "TCI", "mean": -1.0}, {"date": "2018-01-07 00:00:00", "centroid_lon": -78.82755662753084, "centroid_lat": 35.048619248676125, "state": "37_North Carolina", "county": "051_Cumberland", "type": "TCI", "mean": -1.0}, {"date": "2018-01-07 00:00:00", "centroid_lon": -76.28398919035592, "centroid_lat": 36.295476673372434, "state": "37_North Carolina", "county": "139_Pasquotank", "type": "TCI", "mean": -1.0}, {"date": "2018-01-07 00:00:00", "centroid_lon": -78.23769498309457, "centroid_lat": 34.07098550405867, "state": "37_North Carolina", "county": "019_Brunswick", "type": "TCI", "mean": -1.0}, {"date": "2018-01-07 00:00:00", "centroid_lon": -78.6550214967499, "centroid_lat": 34.26564889136196, "state": "37_North Carolina", "county": "047_Columbus", "type": "TCI", "mean": -1.0}, {"date": "2018-01-07 00:00:00", "centroid_lon": -77.67576148339715, "centroid_lat": 35.48500256688326, "state": "37_North Carolina", "county": "079_Greene", "type": "TCI", "mean": -1.0}, {"date": "2018-01-07 00:00:00", "centroid_lon": -77.37449546409213, "centroid_lat": 35.59329582354394, "state": "37_North Carolina", "county": "147_Pitt", "type": "TCI", "mean": -1.0}, {"date": "2018-01-07 00:00:00", "centroid_lon": -83.49278243023281, "centroid_lat": 35.486754609957664, "state": "37_North Carolina", "county": "173_Swain", "type": "TCI", "mean": -1.0}, {"date": "2018-01-07 00:00:00", "centroid_lon": -76.65889147213684, "centroid_lat": 34.83573000222429, "state": "37_North Carolina", "county": "031_Carteret", "type": "TCI", "mean": -1.0}, {"date": "2018-01-07 00:00:00", "centroid_lon": -83.42212187241233, "centroid_lat": 35.15047456374847, "state": "37_North Carolina", "county": "113_Macon", "type": "TCI", "mean": -1.0}, {"date": "2018-01-07 00:00:00", "centroid_lon": -79.39944023393663, "centroid_lat": 36.04373147445877, "state": "37_North Carolina", "county": "001_Alamance", "type": "TCI", "mean": -1.0}, {"date": "2018-01-07 00:00:00", "centroid_lon": -81.69643780642517, "centroid_lat": 36.23109566102052, "state": "37_North Carolina", "county": "189_Watauga", "type": "TCI", "mean": -1.0}, {"date": "2018-01-07 00:00:00", "centroid_lon": -82.16363888311928, "centroid_lat": 36.0132968693219, "state": "37_North Carolina", "county": "121_Mitchell", "type": "TCI", "mean": -1.0}, {"date": "2018-01-07 00:00:00", "centroid_lon": -77.90509380950779, "centroid_lat": 34.52481543223723, "state": "37_North Carolina", "county": "141_Pender", "type": "TCI", "mean": -1.0}, {"date": "2018-01-07 00:00:00", "centroid_lon": -82.98219390643509, "centroid_lat": 35.5560422976075, "state": "37_North Carolina", "county": "087_Haywood", "type": "TCI", "mean": -1.0}, {"date": "2018-01-07 00:00:00", "centroid_lon": -79.10392204505949, "centroid_lat": 34.64021397255586, "state": "37_North Carolina", "county": "155_Robeson", "type": "TCI", "mean": -1.0}, {"date": "2018-01-07 00:00:00", "centroid_lon": -80.8734402807821, "centroid_lat": 35.80702693041323, "state": "37_North Carolina", "county": "097_Iredell", "type": "TCI", "mean": -1.0}, {"date": "2018-01-07 00:00:00", "centroid_lon": -80.2394999333303, "centroid_lat": 36.40189240318627, "state": "37_North Carolina", "county": "169_Stokes", "type": "TCI", "mean": -1.0}, {"date": "2018-01-07 00:00:00", "centroid_lon": -80.53071999601, "centroid_lat": 34.98840747141903, "state": "37_North Carolina", "county": "179_Union", "type": "TCI", "mean": -1.0}, {"date": "2018-01-07 00:00:00", "centroid_lon": -80.55186546381164, "centroid_lat": 35.386786586708105, "state": "37_North Carolina", "county": "025_Cabarrus", "type": "TCI", "mean": -1.0}, {"date": "2018-01-07 00:00:00", "centroid_lon": -81.21507007166129, "centroid_lat": 35.662042229871325, "state": "37_North Carolina", "county": "035_Catawba", "type": "TCI", "mean": -1.0}, {"date": "2018-01-07 00:00:00", "centroid_lon": -76.44114255578744, "centroid_lat": 36.20584815803746, "state": "37_North Carolina", "county": "143_Perquimans", "type": "TCI", "mean": -1.0}, {"date": "2018-01-07 00:00:00", "centroid_lon": -78.0039964664789, "centroid_lat": 35.36396439707785, "state": "37_North Carolina", "county": "191_Wayne", "type": "TCI", "mean": -1.0}, {"date": "2018-01-07 00:00:00", "centroid_lon": -79.33353354686407, "centroid_lat": 36.393172437128015, "state": "37_North Carolina", "county": "033_Caswell", "type": "TCI", "mean": -1.0}, {"date": "2018-01-07 00:00:00", "centroid_lon": -78.10668108358892, "centroid_lat": 36.39652057647641, "state": "37_North Carolina", "county": "185_Warren", "type": "TCI", "mean": -1.0}, {"date": "2018-01-07 00:00:00", "centroid_lon": -76.57747821838238, "centroid_lat": 35.82258903626302, "state": "37_North Carolina", "county": "187_Washington", "type": "TCI", "mean": -1.0}, {"date": "2018-01-07 00:00:00", "centroid_lon": -81.22350912533818, "centroid_lat": 35.4855808728018, "state": "37_North Carolina", "county": "109_Lincoln", "type": "TCI", "mean": -1.0}, {"date": "2018-01-07 00:00:00", "centroid_lon": -80.66523626238177, "centroid_lat": 36.16053315724505, "state": "37_North Carolina", "county": "197_Yadkin", "type": "TCI", "mean": -1.0}, {"date": "2018-01-07 00:00:00", "centroid_lon": -79.78890757944049, "centroid_lat": 36.07946834971741, "state": "37_North Carolina", "county": "081_Guilford", "type": "TCI", "mean": -1.0}, {"date": "2018-01-07 00:00:00", "centroid_lon": -80.83277923218343, "centroid_lat": 35.24671331460535, "state": "37_North Carolina", "county": "119_Mecklenburg", "type": "TCI", "mean": -1.0}, {"date": "2018-01-07 00:00:00", "centroid_lon": -80.68812364833519, "centroid_lat": 36.4147728053525, "state": "37_North Carolina", "county": "171_Surry", "type": "TCI", "mean": -1.0}, {"date": "2018-01-07 00:00:00", "centroid_lon": -78.40792609052453, "centroid_lat": 36.364898765558756, "state": "37_North Carolina", "county": "181_Vance", "type": "TCI", "mean": -1.0}, {"date": "2018-01-07 00:00:00", "centroid_lon": -81.1279092967382, "centroid_lat": 36.491293653884796, "state": "37_North Carolina", "county": "005_Alleghany", "type": "TCI", "mean": -1.0}, {"date": "2018-01-07 00:00:00", "centroid_lon": -76.60789635960934, "centroid_lat": 36.15083674751782, "state": "37_North Carolina", "county": "041_Chowan", "type": "TCI", "mean": -1.0}, {"date": "2018-01-07 00:00:00", "centroid_lon": -77.93300726449544, "centroid_lat": 34.93653802042311, "state": "37_North Carolina", "county": "061_Duplin", "type": "TCI", "mean": -1.0}, {"date": "2018-01-07 00:00:00", "centroid_lon": -81.17701966635214, "centroid_lat": 35.92102819212213, "state": "37_North Carolina", "county": "003_Alexander", "type": "TCI", "mean": -1.0}, {"date": "2018-01-07 00:00:00", "centroid_lon": -81.18028428807236, "centroid_lat": 35.29435358631589, "state": "37_North Carolina", "county": "071_Gaston", "type": "TCI", "mean": -1.0}, {"date": "2018-01-07 00:00:00", "centroid_lon": -76.7004672958838, "centroid_lat": 36.44490682122381, "state": "37_North Carolina", "county": "073_Gates", "type": "TCI", "mean": -1.0}, {"date": "2018-01-07 00:00:00", "centroid_lon": -79.77499283885612, "centroid_lat": 36.396013723833434, "state": "37_North Carolina", "county": "157_Rockingham", "type": "TCI", "mean": -1.0}, {"date": "2018-01-07 00:00:00", "centroid_lon": -77.91866574431374, "centroid_lat": 35.70514620035891, "state": "37_North Carolina", "county": "195_Wilson", "type": "TCI", "mean": -1.0}, {"date": "2018-01-07 00:00:00", "centroid_lon": -79.80600737122685, "centroid_lat": 35.710340053646895, "state": "37_North Carolina", "county": "151_Randolph", "type": "TCI", "mean": -1.0}, {"date": "2018-01-07 00:00:00", "centroid_lon": -80.25629771983725, "centroid_lat": 36.13062135156729, "state": "37_North Carolina", "county": "067_Forsyth", "type": "TCI", "mean": -1.0}, {"date": "2018-01-07 00:00:00", "centroid_lon": -81.55554656739825, "centroid_lat": 35.33408479895233, "state": "37_North Carolina", "county": "045_Cleveland", "type": "TCI", "mean": -1.0}, {"date": "2018-01-07 00:00:00", "centroid_lon": -77.88471177124862, "centroid_lat": 34.23277287573914, "state": "37_North Carolina", "county": "129_New Hanover", "type": "TCI", "mean": -1.0}, {"date": "2018-01-07 00:00:00", "centroid_lon": -80.25098429450291, "centroid_lat": 35.31198126499319, "state": "37_North Carolina", "county": "167_Stanly", "type": "TCI", "mean": -1.0}, {"date": "2018-01-07 00:00:00", "centroid_lon": -78.87662142973507, "centroid_lat": 36.03601682076316, "state": "37_North Carolina", "county": "063_Durham", "type": "TCI", "mean": -1.0}, {"date": "2018-01-07 00:00:00", "centroid_lon": -79.12065991857999, "centroid_lat": 36.061104749007065, "state": "37_North Carolina", "county": "135_Orange", "type": "TCI", "mean": -1.0}, {"date": "2018-01-07 00:00:00", "centroid_lon": -81.9225833921793, "centroid_lat": 36.07654208790323, "state": "37_North Carolina", "county": "011_Avery", "type": "TCI", "mean": -1.0}, {"date": "2018-01-07 00:00:00", "centroid_lon": -78.65272269937773, "centroid_lat": 36.304049485932964, "state": "37_North Carolina", "county": "077_Granville", "type": "TCI", "mean": -1.0}]