[{"date": "2018-07-30 00:00:00", "centroid_lon": -71.62254153850535, "centroid_lat": 41.46972321248195, "state": "44_Rhode Island", "county": "009_Washington", "type": "tasmin", "mean": 290.9212210518973}, {"date": "2018-07-30 00:00:00", "centroid_lon": -71.57999402630503, "centroid_lat": 41.87214104296169, "state": "44_Rhode Island", "county": "007_Providence", "type": "tasmin", "mean": 289.1935570126488}, {"date": "2018-07-30 00:00:00", "centroid_lon": -71.59307644720491, "centroid_lat": 41.672180981458794, "state": "44_Rhode Island", "county": "003_Kent", "type": "tasmin", "mean": 291.32427978515625}, {"date": "2018-07-30 00:00:00", "centroid_lon": -71.23679569247565, "centroid_lat": 41.556386859020776, "state": "44_Rhode Island", "county": "005_Newport", "type": "tasmin", "mean": 289.35398646763394}]